xcloudmanager/__init__.py
xcloudmanager/xcloudmanager.py
xcloudmanager/resources/XCloudJDBC-2.10.6.7.jar
xcloudmanager/resources/XCloudJDBC_SP_Procedure_Parser-0.1.3.jar
xcloudmanager/resources/libthrift-0.9.2.jar
xcloudmanager/resources/log4j-1.2.17.jar
xcloudmanager/resources/lz4-1.3.0.jar
xcloudmanager/resources/slf4j-api-1.7.5.jar
xcloudmanager/resources/slf4j-log4j12-1.7.5.jar
xcloudmanager/resources/slf4j-simple-1.7.5.jar
xcloudmanager-0.3.0.dist-info/METADATA
xcloudmanager-0.3.0.dist-info/WHEEL
xcloudmanager-0.3.0.dist-info/top_level.txt
xcloudmanager-0.3.0.dist-info/RECORD
